README.md
setup.py
allencrf/__init__.py
allencrf/conditional_random_field.py
allencrf/viterbi.py
allencrf.egg-info/PKG-INFO
allencrf.egg-info/SOURCES.txt
allencrf.egg-info/dependency_links.txt
allencrf.egg-info/requires.txt
allencrf.egg-info/top_level.txt