Metadata-Version: 2.1
Name: allencrf
Version: 1.0.2
Summary: An PyTorch CRF implementation extracted from AllenNLP
Home-page: https://github.com/lighttag/allencrf
Author: Tal Perry / Joel Grus
Author-email: tal@lighttag.io
License: Apache 2.0
Platform: UNKNOWN
Classifier: License :: OSI Approved :: Apache Software License
Classifier: Programming Language :: Python :: 3
Classifier: Programming Language :: Python :: 3.7
